pandora_ai/__init__.py
pandora_ai/config.json
pandora_ai/console.py
pandora_ai/get_text.py
pandora_ai/get_webdriver.py
pandora_ai/google_search.py
pandora_ai/pandora_agent.py
pandora_ai/regex_tools.py
pandora_ai/retrieval.py
pandora_ai/retriever.py
pandora_ai-0.0.43.dist-info/LICENSE
pandora_ai-0.0.43.dist-info/METADATA
pandora_ai-0.0.43.dist-info/WHEEL
pandora_ai-0.0.43.dist-info/top_level.txt
pandora_ai-0.0.43.dist-info/RECORD
