Metadata-Version: 2.1
Name: pandora_ai
Version: 0.0.43
Summary: GPT4-powered python interpreter / AI assistant
Home-page: https://github.com/B4PT0R/pandora_ai
Author: Baptiste Ferrand
Author-email: bferrand.maths@gmail.com
Classifier: Programming Language :: Python :: 3
Classifier: License :: OSI Approved :: GNU Affero General Public License v3 or later (AGPLv3+)
Classifier: Operating System :: OS Independent
Requires-Python: >=3.6
License-File: LICENSE
Requires-Dist: selenium
Requires-Dist: get-gecko-driver
Requires-Dist: beautifulsoup4
Requires-Dist: google-api-python-client
Requires-Dist: objdict-bf
Requires-Dist: odfpy
Requires-Dist: openai
Requires-Dist: PyPDF2
Requires-Dist: python-docx
Requires-Dist: requests
Requires-Dist: tiktoken
Requires-Dist: pydub
